{
  "clowns": [],
  "assignedRequests": [],
  "requests": [
    {
      "parentName": "Amber",
      "childName": "Laura",
      "numberInAttendance": "19",
      "address": "9845 Wallow rd",
      "eventDate": "2021-08-27",
      "eventDuration": "4",
      "id": 1
    },
    {
      "parentName": "Michael",
      "childName": "Junior",
      "numberInAttendance": "10",
      "address": "6769 Beach Ave",
      "eventDate": "2021-09-01",
      "eventDuration": "2",
      "id": 2
    },
    {
      "parentName": "Melissa",
      "childName": "Anne",
      "numberInAttendance": "23",
      "address": "4972 Alley St.",
      "eventDate": "2021-08-28",
      "eventDuration": "2",
      "id": 3
    }
  ]
}